GreekStemming/GreekStemming.py
GreekStemming/__init__.py
GreekStemming-1.0.0.dist-info/METADATA
GreekStemming-1.0.0.dist-info/WHEEL
GreekStemming-1.0.0.dist-info/top_level.txt
GreekStemming-1.0.0.dist-info/RECORD
