Metadata-Version: 2.1
Name: GreekStemming
Version: 1.0.0
Summary: Greek Stemming algorithm based on the paper of George Ntais.
Home-page: UNKNOWN
Author: Giorgos - Marios Patelis
Author-email: pgiorgosmarios@gmail.com
License: UNKNOWN
Platform: UNKNOWN
